{
  "spot": "Schellinkhout",
  "generatedAt": "2026-04-12T11:20:22+00:00",
  "current": {
    "windKn": 17.6,
    "gustKn": 24.5,
    "dirDeg": 216
  },
  "actuals": [
    {
      "time": "02:00",
      "windKn": 11.8,
      "gustKn": 15.3,
      "dirDeg": 237
    },
    {
      "time": "02:10",
      "windKn": 9.8,
      "gustKn": 12.9,
      "dirDeg": 228
    },
    {
      "time": "02:20",
      "windKn": 10.6,
      "gustKn": 14.7,
      "dirDeg": 232
    },
    {
      "time": "02:30",
      "windKn": 10.3,
      "gustKn": 14.3,
      "dirDeg": 227
    },
    {
      "time": "02:40",
      "windKn": 9.8,
      "gustKn": 13.7,
      "dirDeg": 222
    },
    {
      "time": "02:50",
      "windKn": 8.7,
      "gustKn": 11.3,
      "dirDeg": 220
    },
    {
      "time": "03:00",
      "windKn": 8.8,
      "gustKn": 13.1,
      "dirDeg": 222
    },
    {
      "time": "03:10",
      "windKn": 9.0,
      "gustKn": 12.9,
      "dirDeg": 221
    },
    {
      "time": "03:20",
      "windKn": 8.9,
      "gustKn": 12.4,
      "dirDeg": 217
    },
    {
      "time": "03:30",
      "windKn": 9.2,
      "gustKn": 13.1,
      "dirDeg": 216
    },
    {
      "time": "03:40",
      "windKn": 8.6,
      "gustKn": 11.2,
      "dirDeg": 206
    },
    {
      "time": "03:50",
      "windKn": 8.1,
      "gustKn": 9.9,
      "dirDeg": 199
    },
    {
      "time": "04:00",
      "windKn": 7.8,
      "gustKn": 9.7,
      "dirDeg": 191
    },
    {
      "time": "04:10",
      "windKn": 8.0,
      "gustKn": 9.4,
      "dirDeg": 193
    },
    {
      "time": "04:20",
      "windKn": 7.8,
      "gustKn": 9.3,
      "dirDeg": 194
    },
    {
      "time": "04:30",
      "windKn": 8.4,
      "gustKn": 10.6,
      "dirDeg": 197
    },
    {
      "time": "04:40",
      "windKn": 8.5,
      "gustKn": 10.0,
      "dirDeg": 197
    },
    {
      "time": "04:50",
      "windKn": 7.2,
      "gustKn": 9.7,
      "dirDeg": 174
    },
    {
      "time": "05:00",
      "windKn": 6.5,
      "gustKn": 8.7,
      "dirDeg": 168
    },
    {
      "time": "05:10",
      "windKn": 7.1,
      "gustKn": 9.7,
      "dirDeg": 166
    },
    {
      "time": "05:20",
      "windKn": 7.5,
      "gustKn": 9.7,
      "dirDeg": 169
    },
    {
      "time": "05:30",
      "windKn": 8.2,
      "gustKn": 11.3,
      "dirDeg": 170
    },
    {
      "time": "05:40",
      "windKn": 10.2,
      "gustKn": 13.5,
      "dirDeg": 168
    },
    {
      "time": "05:50",
      "windKn": 11.8,
      "gustKn": 15.8,
      "dirDeg": 169
    },
    {
      "time": "06:00",
      "windKn": 12.2,
      "gustKn": 16.5,
      "dirDeg": 174
    },
    {
      "time": "06:10",
      "windKn": 10.8,
      "gustKn": 13.7,
      "dirDeg": 176
    },
    {
      "time": "06:20",
      "windKn": 9.9,
      "gustKn": 12.3,
      "dirDeg": 179
    },
    {
      "time": "06:30",
      "windKn": 9.2,
      "gustKn": 11.6,
      "dirDeg": 182
    },
    {
      "time": "06:40",
      "windKn": 8.5,
      "gustKn": 10.3,
      "dirDeg": 182
    },
    {
      "time": "06:50",
      "windKn": 8.8,
      "gustKn": 11.4,
      "dirDeg": 181
    },
    {
      "time": "07:00",
      "windKn": 9.0,
      "gustKn": 11.5,
      "dirDeg": 177
    },
    {
      "time": "07:10",
      "windKn": 8.7,
      "gustKn": 12.3,
      "dirDeg": 176
    },
    {
      "time": "07:20",
      "windKn": 9.3,
      "gustKn": 13.1,
      "dirDeg": 176
    },
    {
      "time": "07:30",
      "windKn": 8.4,
      "gustKn": 10.8,
      "dirDeg": 174
    },
    {
      "time": "07:40",
      "windKn": 9.7,
      "gustKn": 13.2,
      "dirDeg": 180
    },
    {
      "time": "07:50",
      "windKn": 10.8,
      "gustKn": 14.0,
      "dirDeg": 176
    },
    {
      "time": "08:00",
      "windKn": 12.2,
      "gustKn": 15.6,
      "dirDeg": 178
    },
    {
      "time": "08:10",
      "windKn": 12.4,
      "gustKn": 17.9,
      "dirDeg": 182
    },
    {
      "time": "08:20",
      "windKn": 13.7,
      "gustKn": 18.1,
      "dirDeg": 182
    },
    {
      "time": "08:30",
      "windKn": 14.3,
      "gustKn": 17.7,
      "dirDeg": 184
    },
    {
      "time": "08:40",
      "windKn": 15.3,
      "gustKn": 20.5,
      "dirDeg": 186
    },
    {
      "time": "08:50",
      "windKn": 14.6,
      "gustKn": 18.9,
      "dirDeg": 185
    },
    {
      "time": "09:00",
      "windKn": 14.3,
      "gustKn": 18.3,
      "dirDeg": 185
    },
    {
      "time": "09:10",
      "windKn": 13.4,
      "gustKn": 17.4,
      "dirDeg": 186
    },
    {
      "time": "09:20",
      "windKn": 13.6,
      "gustKn": 16.9,
      "dirDeg": 188
    },
    {
      "time": "09:30",
      "windKn": 16.1,
      "gustKn": 23.4,
      "dirDeg": 197
    },
    {
      "time": "09:40",
      "windKn": 17.9,
      "gustKn": 23.4,
      "dirDeg": 201
    },
    {
      "time": "09:50",
      "windKn": 16.3,
      "gustKn": 21.2,
      "dirDeg": 199
    },
    {
      "time": "10:00",
      "windKn": 18.6,
      "gustKn": 24.0,
      "dirDeg": 202
    },
    {
      "time": "10:10",
      "windKn": 16.5,
      "gustKn": 23.4,
      "dirDeg": 205
    },
    {
      "time": "10:20",
      "windKn": 19.3,
      "gustKn": 25.0,
      "dirDeg": 205
    },
    {
      "time": "10:30",
      "windKn": 18.8,
      "gustKn": 27.0,
      "dirDeg": 207
    },
    {
      "time": "10:40",
      "windKn": 18.5,
      "gustKn": 24.6,
      "dirDeg": 210
    },
    {
      "time": "10:50",
      "windKn": 19.7,
      "gustKn": 25.3,
      "dirDeg": 209
    },
    {
      "time": "11:00",
      "windKn": 18.8,
      "gustKn": 25.6,
      "dirDeg": 210
    },
    {
      "time": "11:10",
      "windKn": 19.5,
      "gustKn": 25.4,
      "dirDeg": 207
    },
    {
      "time": "11:20",
      "windKn": 15.7,
      "gustKn": 22.4,
      "dirDeg": 215
    },
    {
      "time": "11:30",
      "windKn": 18.8,
      "gustKn": 26.5,
      "dirDeg": 210
    },
    {
      "time": "11:40",
      "windKn": 19.2,
      "gustKn": 25.6,
      "dirDeg": 207
    },
    {
      "time": "11:50",
      "windKn": 19.3,
      "gustKn": 24.9,
      "dirDeg": 209
    },
    {
      "time": "12:00",
      "windKn": 18.6,
      "gustKn": 26.2,
      "dirDeg": 214
    },
    {
      "time": "12:10",
      "windKn": 18.0,
      "gustKn": 24.3,
      "dirDeg": 214
    },
    {
      "time": "12:20",
      "windKn": 19.9,
      "gustKn": 26.1,
      "dirDeg": 213
    },
    {
      "time": "12:30",
      "windKn": 17.7,
      "gustKn": 24.4,
      "dirDeg": 213
    },
    {
      "time": "12:40",
      "windKn": 19.6,
      "gustKn": 25.5,
      "dirDeg": 209
    },
    {
      "time": "12:50",
      "windKn": 17.8,
      "gustKn": 23.9,
      "dirDeg": 210
    },
    {
      "time": "13:00",
      "windKn": 18.4,
      "gustKn": 25.7,
      "dirDeg": 213
    },
    {
      "time": "13:10",
      "windKn": 17.6,
      "gustKn": 24.5,
      "dirDeg": 216
    }
  ]
}