{
  "spot": "Schellinkhout",
  "generatedAt": "2026-04-10T22:24:58+00:00",
  "current": {
    "windKn": 9.5,
    "gustKn": 14.4,
    "dirDeg": 96
  },
  "hourly": [
    {
      "hour": 22,
      "forecastWindKn": 9.1,
      "forecastGustKn": 13.6,
      "dirDeg": 96,
      "waveM": 0.04,
      "wavePeriodS": 1.5,
      "tempC": 7.4,
      "rainMm": 0.0
    },
    {
      "hour": 23,
      "forecastWindKn": 10.5,
      "forecastGustKn": 16.3,
      "dirDeg": 100,
      "waveM": 0.26,
      "wavePeriodS": 1.5,
      "tempC": 8.0,
      "rainMm": 0.0
    }
  ]
}