{
  "spot": "IJmuiden",
  "generatedAt": "2026-04-23T01:24:45+00:00",
  "current": {
    "windKn": 5.4,
    "gustKn": 9.9,
    "dirDeg": 60
  },
  "hourly": [
    {
      "hour": 0,
      "forecastWindKn": 5.4,
      "forecastGustKn": 11.5,
      "dirDeg": 53,
      "waveM": 0.58,
      "wavePeriodS": 4.2,
      "tempC": 7.7,
      "rainMm": 0.0,
      "cloudPct": 0
    },
    {
      "hour": 1,
      "forecastWindKn": 5.6,
      "forecastGustKn": 10.1,
      "dirDeg": 60,
      "waveM": 0.56,
      "wavePeriodS": 4.2,
      "tempC": 7.3,
      "rainMm": 0.0,
      "cloudPct": 0
    },
    {
      "hour": 2,
      "forecastWindKn": 5.1,
      "forecastGustKn": 9.9,
      "dirDeg": 53,
      "waveM": 0.54,
      "wavePeriodS": 4.2,
      "tempC": 6.9,
      "rainMm": 0.0,
      "cloudPct": 0
    },
    {
      "hour": 3,
      "forecastWindKn": 4.5,
      "forecastGustKn": 8.6,
      "dirDeg": 46,
      "waveM": 0.52,
      "wavePeriodS": 4.2,
      "tempC": 6.5,
      "rainMm": 0.0,
      "cloudPct": 0
    },
    {
      "hour": 4,
      "forecastWindKn": 4.3,
      "forecastGustKn": 7.4,
      "dirDeg": 32,
      "waveM": 0.52,
      "wavePeriodS": 4.2,
      "tempC": 5.9,
      "rainMm": 0.0,
      "cloudPct": 0
    },
    {
      "hour": 5,
      "forecastWindKn": 5.6,
      "forecastGustKn": 9.9,
      "dirDeg": 15,
      "waveM": 0.5,
      "wavePeriodS": 4.2,
      "tempC": 6.2,
      "rainMm": 0.0,
      "cloudPct": 0
    },
    {
      "hour": 6,
      "forecastWindKn": 6.4,
      "forecastGustKn": 12.4,
      "dirDeg": 21,
      "waveM": 0.48,
      "wavePeriodS": 4.3,
      "tempC": 7.4,
      "rainMm": 0.0,
      "cloudPct": 4
    },
    {
      "hour": 7,
      "forecastWindKn": 5.2,
      "forecastGustKn": 12.1,
      "dirDeg": 23,
      "waveM": 0.48,
      "wavePeriodS": 4.3,
      "tempC": 8.4,
      "rainMm": 0.0,
      "cloudPct": 0
    },
    {
      "hour": 8,
      "forecastWindKn": 5.4,
      "forecastGustKn": 11.3,
      "dirDeg": 359,
      "waveM": 0.5,
      "wavePeriodS": 4.3,
      "tempC": 9.8,
      "rainMm": 0.0,
      "cloudPct": 25
    },
    {
      "hour": 9,
      "forecastWindKn": 7.4,
      "forecastGustKn": 14.6,
      "dirDeg": 341,
      "waveM": 0.5,
      "wavePeriodS": 4.3,
      "tempC": 10.7,
      "rainMm": 0.0,
      "cloudPct": 25
    },
    {
      "hour": 10,
      "forecastWindKn": 8.4,
      "forecastGustKn": 15.9,
      "dirDeg": 337,
      "waveM": 0.52,
      "wavePeriodS": 4.3,
      "tempC": 11.1,
      "rainMm": 0.0,
      "cloudPct": 54
    },
    {
      "hour": 11,
      "forecastWindKn": 9.1,
      "forecastGustKn": 17.5,
      "dirDeg": 338,
      "waveM": 0.52,
      "wavePeriodS": 4.2,
      "tempC": 11.7,
      "rainMm": 0.0,
      "cloudPct": 5
    },
    {
      "hour": 12,
      "forecastWindKn": 10.9,
      "forecastGustKn": 20.2,
      "dirDeg": 341,
      "waveM": 0.54,
      "wavePeriodS": 4.2,
      "tempC": 12.2,
      "rainMm": 0.0,
      "cloudPct": 1
    },
    {
      "hour": 13,
      "forecastWindKn": 11.7,
      "forecastGustKn": 21.6,
      "dirDeg": 343,
      "waveM": 0.58,
      "wavePeriodS": 4.1,
      "tempC": 12.5,
      "rainMm": 0.0,
      "cloudPct": 5
    },
    {
      "hour": 14,
      "forecastWindKn": 11.3,
      "forecastGustKn": 21.4,
      "dirDeg": 342,
      "waveM": 0.66,
      "wavePeriodS": 3.9,
      "tempC": 12.4,
      "rainMm": 0.0,
      "cloudPct": 26
    },
    {
      "hour": 15,
      "forecastWindKn": 10.7,
      "forecastGustKn": 20.8,
      "dirDeg": 345,
      "waveM": 0.74,
      "wavePeriodS": 3.8,
      "tempC": 12.1,
      "rainMm": 0.0,
      "cloudPct": 60
    },
    {
      "hour": 16,
      "forecastWindKn": 10.7,
      "forecastGustKn": 20.0,
      "dirDeg": 351,
      "waveM": 0.76,
      "wavePeriodS": 4.0,
      "tempC": 11.9,
      "rainMm": 0.0,
      "cloudPct": 36
    },
    {
      "hour": 17,
      "forecastWindKn": 10.5,
      "forecastGustKn": 19.6,
      "dirDeg": 352,
      "waveM": 0.74,
      "wavePeriodS": 4.1,
      "tempC": 11.6,
      "rainMm": 0.0,
      "cloudPct": 1
    },
    {
      "hour": 18,
      "forecastWindKn": 10.7,
      "forecastGustKn": 19.2,
      "dirDeg": 355,
      "waveM": 0.74,
      "wavePeriodS": 4.1,
      "tempC": 11.0,
      "rainMm": 0.0,
      "cloudPct": 0
    },
    {
      "hour": 19,
      "forecastWindKn": 7.8,
      "forecastGustKn": 19.2,
      "dirDeg": 6,
      "waveM": 0.72,
      "wavePeriodS": 4.2,
      "tempC": 10.2,
      "rainMm": 0.0,
      "cloudPct": 0
    },
    {
      "hour": 20,
      "forecastWindKn": 6.6,
      "forecastGustKn": 13.6,
      "dirDeg": 17,
      "waveM": 0.72,
      "wavePeriodS": 4.3,
      "tempC": 9.3,
      "rainMm": 0.0,
      "cloudPct": 0
    },
    {
      "hour": 21,
      "forecastWindKn": 6.2,
      "forecastGustKn": 12.1,
      "dirDeg": 18,
      "waveM": 0.72,
      "wavePeriodS": 4.4,
      "tempC": 8.3,
      "rainMm": 0.0,
      "cloudPct": 0
    },
    {
      "hour": 22,
      "forecastWindKn": 6.8,
      "forecastGustKn": 13.0,
      "dirDeg": 23,
      "waveM": 0.72,
      "wavePeriodS": 4.4,
      "tempC": 7.3,
      "rainMm": 0.0,
      "cloudPct": 0
    },
    {
      "hour": 23,
      "forecastWindKn": 5.8,
      "forecastGustKn": 12.4,
      "dirDeg": 20,
      "waveM": 0.72,
      "wavePeriodS": 4.6,
      "tempC": 7.0,
      "rainMm": 0.0,
      "cloudPct": 50
    }
  ]
}