{
  "spot": "IJmuiden",
  "generatedAt": "2026-04-21T10:09:03+00:00",
  "current": {
    "windKn": 11.1,
    "gustKn": 22.0,
    "dirDeg": 66
  },
  "hourly": [
    {
      "hour": 0,
      "forecastWindKn": 8.7,
      "forecastGustKn": 15.9,
      "dirDeg": 37,
      "waveM": 0.72,
      "wavePeriodS": 4.3,
      "tempC": 7.5,
      "rainMm": 0.0,
      "cloudPct": 100
    },
    {
      "hour": 1,
      "forecastWindKn": 8.2,
      "forecastGustKn": 14.2,
      "dirDeg": 40,
      "waveM": 0.7,
      "wavePeriodS": 4.3,
      "tempC": 6.9,
      "rainMm": 0.0,
      "cloudPct": 0
    },
    {
      "hour": 2,
      "forecastWindKn": 7.2,
      "forecastGustKn": 13.4,
      "dirDeg": 55,
      "waveM": 0.68,
      "wavePeriodS": 4.2,
      "tempC": 6.6,
      "rainMm": 0.0,
      "cloudPct": 74
    },
    {
      "hour": 3,
      "forecastWindKn": 7.4,
      "forecastGustKn": 14.0,
      "dirDeg": 59,
      "waveM": 0.64,
      "wavePeriodS": 4.2,
      "tempC": 6.5,
      "rainMm": 0.0,
      "cloudPct": 100
    },
    {
      "hour": 4,
      "forecastWindKn": 6.6,
      "forecastGustKn": 12.1,
      "dirDeg": 53,
      "waveM": 0.62,
      "wavePeriodS": 4.1,
      "tempC": 5.3,
      "rainMm": 0.0,
      "cloudPct": 0
    },
    {
      "hour": 5,
      "forecastWindKn": 8.2,
      "forecastGustKn": 15.2,
      "dirDeg": 68,
      "waveM": 0.58,
      "wavePeriodS": 4.0,
      "tempC": 5.1,
      "rainMm": 0.0,
      "cloudPct": 0
    },
    {
      "hour": 6,
      "forecastWindKn": 7.6,
      "forecastGustKn": 14.8,
      "dirDeg": 66,
      "waveM": 0.58,
      "wavePeriodS": 3.8,
      "tempC": 6.0,
      "rainMm": 0.0,
      "cloudPct": 0
    },
    {
      "hour": 7,
      "forecastWindKn": 9.3,
      "forecastGustKn": 18.3,
      "dirDeg": 65,
      "waveM": 0.58,
      "wavePeriodS": 3.8,
      "tempC": 7.6,
      "rainMm": 0.0,
      "cloudPct": 0
    },
    {
      "hour": 8,
      "forecastWindKn": 9.9,
      "forecastGustKn": 19.6,
      "dirDeg": 65,
      "waveM": 0.58,
      "wavePeriodS": 3.7,
      "tempC": 8.7,
      "rainMm": 0.0,
      "cloudPct": 0
    },
    {
      "hour": 9,
      "forecastWindKn": 10.5,
      "forecastGustKn": 21.0,
      "dirDeg": 66,
      "waveM": 0.58,
      "wavePeriodS": 3.7,
      "tempC": 9.7,
      "rainMm": 0.0,
      "cloudPct": 0
    },
    {
      "hour": 10,
      "forecastWindKn": 11.1,
      "forecastGustKn": 22.0,
      "dirDeg": 66,
      "waveM": 0.6,
      "wavePeriodS": 3.7,
      "tempC": 10.9,
      "rainMm": 0.0,
      "cloudPct": 0
    },
    {
      "hour": 11,
      "forecastWindKn": 10.9,
      "forecastGustKn": 22.0,
      "dirDeg": 65,
      "waveM": 0.6,
      "wavePeriodS": 3.7,
      "tempC": 12.2,
      "rainMm": 0.0,
      "cloudPct": 0
    },
    {
      "hour": 12,
      "forecastWindKn": 11.5,
      "forecastGustKn": 23.3,
      "dirDeg": 66,
      "waveM": 0.6,
      "wavePeriodS": 3.7,
      "tempC": 13.2,
      "rainMm": 0.0,
      "cloudPct": 0
    },
    {
      "hour": 13,
      "forecastWindKn": 11.1,
      "forecastGustKn": 23.3,
      "dirDeg": 64,
      "waveM": 0.58,
      "wavePeriodS": 3.7,
      "tempC": 13.9,
      "rainMm": 0.0,
      "cloudPct": 0
    },
    {
      "hour": 14,
      "forecastWindKn": 11.1,
      "forecastGustKn": 22.5,
      "dirDeg": 64,
      "waveM": 0.58,
      "wavePeriodS": 3.7,
      "tempC": 14.5,
      "rainMm": 0.0,
      "cloudPct": 0
    },
    {
      "hour": 15,
      "forecastWindKn": 11.1,
      "forecastGustKn": 22.4,
      "dirDeg": 63,
      "waveM": 0.62,
      "wavePeriodS": 3.8,
      "tempC": 14.7,
      "rainMm": 0.0,
      "cloudPct": 0
    },
    {
      "hour": 16,
      "forecastWindKn": 10.9,
      "forecastGustKn": 22.2,
      "dirDeg": 61,
      "waveM": 0.68,
      "wavePeriodS": 3.8,
      "tempC": 14.6,
      "rainMm": 0.0,
      "cloudPct": 0
    },
    {
      "hour": 17,
      "forecastWindKn": 10.3,
      "forecastGustKn": 21.6,
      "dirDeg": 56,
      "waveM": 0.76,
      "wavePeriodS": 4.0,
      "tempC": 14.1,
      "rainMm": 0.0,
      "cloudPct": 0
    },
    {
      "hour": 18,
      "forecastWindKn": 8.9,
      "forecastGustKn": 19.8,
      "dirDeg": 44,
      "waveM": 0.78,
      "wavePeriodS": 4.0,
      "tempC": 13.1,
      "rainMm": 0.0,
      "cloudPct": 0
    },
    {
      "hour": 19,
      "forecastWindKn": 10.1,
      "forecastGustKn": 18.3,
      "dirDeg": 43,
      "waveM": 0.76,
      "wavePeriodS": 4.0,
      "tempC": 11.6,
      "rainMm": 0.0,
      "cloudPct": 0
    },
    {
      "hour": 20,
      "forecastWindKn": 10.9,
      "forecastGustKn": 19.8,
      "dirDeg": 48,
      "waveM": 0.7,
      "wavePeriodS": 4.0,
      "tempC": 10.4,
      "rainMm": 0.0,
      "cloudPct": 0
    },
    {
      "hour": 21,
      "forecastWindKn": 9.5,
      "forecastGustKn": 19.8,
      "dirDeg": 53,
      "waveM": 0.66,
      "wavePeriodS": 3.9,
      "tempC": 9.5,
      "rainMm": 0.0,
      "cloudPct": 0
    },
    {
      "hour": 22,
      "forecastWindKn": 8.9,
      "forecastGustKn": 17.3,
      "dirDeg": 55,
      "waveM": 0.62,
      "wavePeriodS": 3.9,
      "tempC": 8.8,
      "rainMm": 0.0,
      "cloudPct": 0
    },
    {
      "hour": 23,
      "forecastWindKn": 6.0,
      "forecastGustKn": 16.3,
      "dirDeg": 55,
      "waveM": 0.56,
      "wavePeriodS": 3.8,
      "tempC": 8.3,
      "rainMm": 0.0,
      "cloudPct": 0
    }
  ]
}