{
  "spot": "IJmuiden",
  "generatedAt": "2026-04-11T22:20:08+00:00",
  "current": {
    "windKn": 15.2,
    "gustKn": 27.6,
    "dirDeg": 228
  },
  "hourly": [
    {
      "hour": 22,
      "forecastWindKn": 15.0,
      "forecastGustKn": 26.8,
      "dirDeg": 228,
      "waveM": 1.22,
      "wavePeriodS": 4.0,
      "tempC": 8.9,
      "rainMm": 0.0
    },
    {
      "hour": 23,
      "forecastWindKn": 13.8,
      "forecastGustKn": 26.8,
      "dirDeg": 231,
      "waveM": 1.4,
      "wavePeriodS": 4.5,
      "tempC": 8.8,
      "rainMm": 0.0
    }
  ]
}