{
  "spot": "Wijk aan Zee",
  "generatedAt": "2026-04-13T23:34:03+00:00",
  "current": {
    "windKn": 0.2,
    "gustKn": 1.7,
    "dirDeg": 259
  },
  "hourly": [
    {
      "hour": 22,
      "forecastWindKn": 2.3,
      "forecastGustKn": 6.8,
      "dirDeg": 184,
      "waveM": 0.06,
      "wavePeriodS": 3.5,
      "tempC": 8.5,
      "rainMm": 0.0
    },
    {
      "hour": 23,
      "forecastWindKn": 0.4,
      "forecastGustKn": 2.9,
      "dirDeg": 259,
      "waveM": 0.06,
      "wavePeriodS": 3.5,
      "tempC": 8.2,
      "rainMm": 0.0
    }
  ]
}