{
  "spot": "Kijkduin",
  "generatedAt": "2026-04-23T05:17:22+00:00",
  "current": {
    "windKn": 4.4,
    "gustKn": 7.1,
    "dirDeg": 336
  },
  "actuals": [
    {
      "time": "02:00",
      "windKn": 2.2,
      "gustKn": 3.0,
      "dirDeg": 6
    },
    {
      "time": "02:10",
      "windKn": 2.5,
      "gustKn": 3.2,
      "dirDeg": 16
    },
    {
      "time": "02:20",
      "windKn": 3.2,
      "gustKn": 4.9,
      "dirDeg": 14
    },
    {
      "time": "02:30",
      "windKn": 3.9,
      "gustKn": 5.9,
      "dirDeg": 4
    },
    {
      "time": "02:40",
      "windKn": 4.4,
      "gustKn": 6.0,
      "dirDeg": 7
    },
    {
      "time": "02:50",
      "windKn": 4.3,
      "gustKn": 6.0,
      "dirDeg": 10
    },
    {
      "time": "03:00",
      "windKn": 4.0,
      "gustKn": 5.8,
      "dirDeg": 8
    },
    {
      "time": "03:10",
      "windKn": 4.0,
      "gustKn": 6.0,
      "dirDeg": 353
    },
    {
      "time": "03:20",
      "windKn": 5.2,
      "gustKn": 7.5,
      "dirDeg": 9
    },
    {
      "time": "03:30",
      "windKn": 4.9,
      "gustKn": 7.2,
      "dirDeg": 8
    },
    {
      "time": "03:40",
      "windKn": 6.3,
      "gustKn": 9.5,
      "dirDeg": 12
    },
    {
      "time": "03:50",
      "windKn": 5.4,
      "gustKn": 7.6,
      "dirDeg": 350
    },
    {
      "time": "04:00",
      "windKn": 4.7,
      "gustKn": 7.0,
      "dirDeg": 336
    },
    {
      "time": "04:10",
      "windKn": 5.4,
      "gustKn": 8.5,
      "dirDeg": 348
    },
    {
      "time": "04:20",
      "windKn": 5.9,
      "gustKn": 8.4,
      "dirDeg": 3
    },
    {
      "time": "04:30",
      "windKn": 5.6,
      "gustKn": 8.2,
      "dirDeg": 17
    },
    {
      "time": "04:40",
      "windKn": 6.8,
      "gustKn": 9.2,
      "dirDeg": 19
    },
    {
      "time": "04:50",
      "windKn": 6.8,
      "gustKn": 8.8,
      "dirDeg": 23
    },
    {
      "time": "05:00",
      "windKn": 5.6,
      "gustKn": 7.9,
      "dirDeg": 20
    },
    {
      "time": "05:10",
      "windKn": 4.4,
      "gustKn": 6.9,
      "dirDeg": 349
    },
    {
      "time": "05:20",
      "windKn": 5.1,
      "gustKn": 7.4,
      "dirDeg": 330
    },
    {
      "time": "05:30",
      "windKn": 3.9,
      "gustKn": 6.0,
      "dirDeg": 338
    },
    {
      "time": "05:40",
      "windKn": 5.4,
      "gustKn": 9.9,
      "dirDeg": 13
    },
    {
      "time": "05:50",
      "windKn": 7.0,
      "gustKn": 10.6,
      "dirDeg": 20
    },
    {
      "time": "06:00",
      "windKn": 5.9,
      "gustKn": 8.6,
      "dirDeg": 18
    },
    {
      "time": "06:10",
      "windKn": 5.6,
      "gustKn": 7.6,
      "dirDeg": 17
    },
    {
      "time": "06:20",
      "windKn": 4.8,
      "gustKn": 7.2,
      "dirDeg": 327
    },
    {
      "time": "06:30",
      "windKn": 3.9,
      "gustKn": 6.2,
      "dirDeg": 335
    },
    {
      "time": "06:40",
      "windKn": 4.0,
      "gustKn": 6.8,
      "dirDeg": 328
    },
    {
      "time": "06:50",
      "windKn": 5.2,
      "gustKn": 7.5,
      "dirDeg": 313
    },
    {
      "time": "07:00",
      "windKn": 4.2,
      "gustKn": 7.2,
      "dirDeg": 350
    },
    {
      "time": "07:10",
      "windKn": 4.4,
      "gustKn": 7.1,
      "dirDeg": 336
    }
  ]
}