{
  "spot": "Kijkduin",
  "generatedAt": "2026-04-17T23:29:49+00:00",
  "current": {
    "windKn": 4.5,
    "gustKn": 5.6,
    "dirDeg": 173
  },
  "hourly": [
    {
      "hour": 22,
      "forecastWindKn": 3.7,
      "forecastGustKn": 4.7,
      "dirDeg": 154,
      "waveM": 0.36,
      "wavePeriodS": 3.8,
      "tempC": 10.6,
      "rainMm": 0.0,
      "cloudPct": 0
    },
    {
      "hour": 23,
      "forecastWindKn": 4.3,
      "forecastGustKn": 5.4,
      "dirDeg": 173,
      "waveM": 0.38,
      "wavePeriodS": 3.8,
      "tempC": 10.2,
      "rainMm": 0.0,
      "cloudPct": 10
    }
  ]
}