{
  "spot": "Kijkduin",
  "generatedAt": "2026-04-12T07:56:24+00:00",
  "current": {
    "windKn": 11.9,
    "gustKn": 20.4,
    "dirDeg": 193
  },
  "hourly": [
    {
      "hour": 0,
      "forecastWindKn": 15.4,
      "forecastGustKn": 24.5,
      "dirDeg": 239,
      "waveM": 1.16,
      "wavePeriodS": 4.8,
      "tempC": 9.1,
      "rainMm": 0.0
    },
    {
      "hour": 1,
      "forecastWindKn": 14.8,
      "forecastGustKn": 22.9,
      "dirDeg": 233,
      "waveM": 1.16,
      "wavePeriodS": 5.0,
      "tempC": 9.1,
      "rainMm": 0.0
    },
    {
      "hour": 2,
      "forecastWindKn": 10.7,
      "forecastGustKn": 17.3,
      "dirDeg": 190,
      "waveM": 1.16,
      "wavePeriodS": 5.1,
      "tempC": 7.1,
      "rainMm": 0.0
    },
    {
      "hour": 3,
      "forecastWindKn": 10.9,
      "forecastGustKn": 17.5,
      "dirDeg": 180,
      "waveM": 1.16,
      "wavePeriodS": 5.2,
      "tempC": 6.6,
      "rainMm": 0.0
    },
    {
      "hour": 4,
      "forecastWindKn": 11.1,
      "forecastGustKn": 18.1,
      "dirDeg": 177,
      "waveM": 1.14,
      "wavePeriodS": 5.2,
      "tempC": 6.7,
      "rainMm": 0.0
    },
    {
      "hour": 5,
      "forecastWindKn": 12.1,
      "forecastGustKn": 20.2,
      "dirDeg": 185,
      "waveM": 1.12,
      "wavePeriodS": 5.2,
      "tempC": 6.7,
      "rainMm": 0.0
    },
    {
      "hour": 6,
      "forecastWindKn": 13.0,
      "forecastGustKn": 21.8,
      "dirDeg": 185,
      "waveM": 1.1,
      "wavePeriodS": 5.2,
      "tempC": 7.1,
      "rainMm": 0.0
    },
    {
      "hour": 7,
      "forecastWindKn": 11.9,
      "forecastGustKn": 21.6,
      "dirDeg": 193,
      "waveM": 1.08,
      "wavePeriodS": 5.1,
      "tempC": 8.0,
      "rainMm": 0.0
    },
    {
      "hour": 8,
      "forecastWindKn": 11.9,
      "forecastGustKn": 20.2,
      "dirDeg": 196,
      "waveM": 1.04,
      "wavePeriodS": 5.1,
      "tempC": 9.3,
      "rainMm": 0.0
    },
    {
      "hour": 9,
      "forecastWindKn": 11.7,
      "forecastGustKn": 20.4,
      "dirDeg": 202,
      "waveM": 1.02,
      "wavePeriodS": 5.1,
      "tempC": 10.6,
      "rainMm": 0.0
    },
    {
      "hour": 10,
      "forecastWindKn": 11.3,
      "forecastGustKn": 20.0,
      "dirDeg": 211,
      "waveM": 0.98,
      "wavePeriodS": 5.1,
      "tempC": 11.9,
      "rainMm": 0.0
    },
    {
      "hour": 11,
      "forecastWindKn": 10.5,
      "forecastGustKn": 19.4,
      "dirDeg": 215,
      "waveM": 0.96,
      "wavePeriodS": 5.1,
      "tempC": 12.9,
      "rainMm": 0.0
    },
    {
      "hour": 12,
      "forecastWindKn": 10.3,
      "forecastGustKn": 18.9,
      "dirDeg": 228,
      "waveM": 0.92,
      "wavePeriodS": 5.1,
      "tempC": 13.2,
      "rainMm": 0.0
    },
    {
      "hour": 13,
      "forecastWindKn": 12.6,
      "forecastGustKn": 21.0,
      "dirDeg": 248,
      "waveM": 0.88,
      "wavePeriodS": 5.1,
      "tempC": 12.2,
      "rainMm": 0.0
    },
    {
      "hour": 14,
      "forecastWindKn": 9.5,
      "forecastGustKn": 21.0,
      "dirDeg": 244,
      "waveM": 0.84,
      "wavePeriodS": 5.1,
      "tempC": 12.7,
      "rainMm": 0.0
    },
    {
      "hour": 15,
      "forecastWindKn": 9.1,
      "forecastGustKn": 16.1,
      "dirDeg": 248,
      "waveM": 0.8,
      "wavePeriodS": 5.1,
      "tempC": 12.7,
      "rainMm": 0.0
    },
    {
      "hour": 16,
      "forecastWindKn": 8.6,
      "forecastGustKn": 15.4,
      "dirDeg": 251,
      "waveM": 0.76,
      "wavePeriodS": 5.1,
      "tempC": 12.3,
      "rainMm": 0.0
    },
    {
      "hour": 17,
      "forecastWindKn": 6.8,
      "forecastGustKn": 14.2,
      "dirDeg": 242,
      "waveM": 0.74,
      "wavePeriodS": 5.1,
      "tempC": 11.8,
      "rainMm": 0.0
    },
    {
      "hour": 18,
      "forecastWindKn": 5.4,
      "forecastGustKn": 11.7,
      "dirDeg": 233,
      "waveM": 0.7,
      "wavePeriodS": 5.2,
      "tempC": 11.4,
      "rainMm": 0.0
    },
    {
      "hour": 19,
      "forecastWindKn": 3.7,
      "forecastGustKn": 8.7,
      "dirDeg": 232,
      "waveM": 0.68,
      "wavePeriodS": 5.2,
      "tempC": 10.8,
      "rainMm": 0.0
    },
    {
      "hour": 20,
      "forecastWindKn": 3.5,
      "forecastGustKn": 5.1,
      "dirDeg": 225,
      "waveM": 0.64,
      "wavePeriodS": 5.2,
      "tempC": 10.1,
      "rainMm": 0.0
    },
    {
      "hour": 21,
      "forecastWindKn": 2.5,
      "forecastGustKn": 4.9,
      "dirDeg": 236,
      "waveM": 0.62,
      "wavePeriodS": 5.2,
      "tempC": 9.7,
      "rainMm": 0.0
    },
    {
      "hour": 22,
      "forecastWindKn": 1.0,
      "forecastGustKn": 3.1,
      "dirDeg": 198,
      "waveM": 0.58,
      "wavePeriodS": 5.2,
      "tempC": 9.8,
      "rainMm": 0.0
    },
    {
      "hour": 23,
      "forecastWindKn": 1.6,
      "forecastGustKn": 2.1,
      "dirDeg": 107,
      "waveM": 0.56,
      "wavePeriodS": 5.1,
      "tempC": 9.9,
      "rainMm": 0.0
    }
  ]
}